geotech-0.1.0a1.dist-info/METADATA
geotech-0.1.0a1.dist-info/WHEEL
geotech-0.1.0a1.dist-info/licenses/LICENSE
geotech/__init__.py
geotech/soil.py
geotech-0.1.0a1.dist-info/RECORD
