Metadata-Version: 2.1
Name: geotech
Version: 0.1.0a1
Summary: A suite of tools for geotechnical engineering.
Author-Email: Sean Daly <the_sean_c@fastmail.com>
License: GNU AGPLv3
Requires-Python: >=3.10
Requires-Dist: numpy>=1.25.2
